tdpy/__init__.py
tdpy/mcmc_depr.py
tdpy/setup.py
tdpy/test.py
tdpy/util.py
tdpy-1.2.dist-info/LICENSE.md
tdpy-1.2.dist-info/METADATA
tdpy-1.2.dist-info/WHEEL
tdpy-1.2.dist-info/top_level.txt
tdpy-1.2.dist-info/RECORD
